jaanca_chronometer/__init__.py
jaanca_chronometer/utils/__init__.py
jaanca_chronometer/utils/helpers/__init__.py
jaanca_chronometer/utils/helpers/chronometer.py
jaanca_chronometer-0.1.6.dist-info/LICENSE.txt
jaanca_chronometer-0.1.6.dist-info/METADATA
jaanca_chronometer-0.1.6.dist-info/WHEEL
jaanca_chronometer-0.1.6.dist-info/top_level.txt
jaanca_chronometer-0.1.6.dist-info/RECORD
