Metadata-Version: 2.1
Name: jaanca-chronometer
Version: 0.1.6
Summary: A tool library created by jaanca that allows measuring the time between two moments in the source code.
Home-page: https://github.com/jaanca/python-libraries/tree/main/jaanca-chronometer
Author: Jaime Andres Cardona Carrillo
Author-email: jacardona@outlook.com
License: MIT License
Keywords: timer stopwatch in interval format for databases
Classifier: Development Status :: 4 - Beta
Classifier: Intended Audience :: Developers
Classifier: Intended Audience :: Information Technology
Classifier: Intended Audience :: System Administrators
Classifier: License :: OSI Approved :: MIT License
Classifier: Operating System :: OS Independent
Classifier: Programming Language :: Python :: 3.10
Classifier: Programming Language :: Python :: 3.11
Classifier: Programming Language :: Python :: 3.8
Classifier: Programming Language :: Python :: 3.9
Classifier: Programming Language :: Python :: 3
Classifier: Programming Language :: Python
Classifier: Topic :: Software Development :: Libraries :: Python Modules
Classifier: Topic :: System :: Monitoring
Classifier: Topic :: Software Development
Classifier: Typing :: Typed
Requires-Python: >=3.8
License-File: LICENSE.txt
